AUTHORS
ChangeLog
LICENSE
README.md
requirements.txt
setup.cfg
setup.py
iddt/__init__.py
iddt/cli.py
iddt/daemon.py
iddt/dispatcher.py
iddt/dispatcher_example.py
iddt/mongo.py
iddt/start-workers.sh
iddt/stop-workers.sh
iddt/utils.py
iddt/worker.py
iddt/worker_example.py
iddt.egg-info/PKG-INFO
iddt.egg-info/SOURCES.txt
iddt.egg-info/dependency_links.txt
iddt.egg-info/not-zip-safe
iddt.egg-info/pbr.json
iddt.egg-info/requires.txt
iddt.egg-info/top_level.txt