Metadata-Version: 1.1
Name: iddt
Version: 0.1.13
Summary: Internet Document Discovery Tool
Home-page: UNKNOWN
Author: Timothy Duffy
Author-email: tim@timduffy.me
License: GPLv3+
Keywords: documents
Platform: UNKNOWN
Classifier: Development Status :: 3 - Alpha
Classifier: Natural Language :: English
Classifier: Operating System :: POSIX :: Linux
Classifier: Programming Language :: Python :: 3 :: Only
Classifier: Intended Audience :: Developers
